fake_bme280/__init__.py
fake_bme280/basic.py
fake_bme280/protocol.py
circuitpython_fake_bme280-1.0.4.dist-info/LICENSE
circuitpython_fake_bme280-1.0.4.dist-info/METADATA
circuitpython_fake_bme280-1.0.4.dist-info/WHEEL
circuitpython_fake_bme280-1.0.4.dist-info/top_level.txt
circuitpython_fake_bme280-1.0.4.dist-info/RECORD
