Metadata-Version: 2.1
Name: circuitpython-fake-bme280
Version: 1.0.4
Summary: BME280 Driver for CircuitPython used for testing functionality with no hardware attached
Author-email: Adafruit Industries <circuitpython@adafruit.com>
License: MIT
Project-URL: Homepage, https://github.com/brentru/CircuitPython_Fake_BME280
Keywords: adafruit,blinka,circuitpython,micropython,fake_bme280,bme280,,test,,fake,,mock,,stub
Classifier: Intended Audience :: Developers
Classifier: Topic :: Software Development :: Libraries
Classifier: Topic :: Software Development :: Embedded Systems
Classifier: Topic :: System :: Hardware
Classifier: License :: OSI Approved :: MIT License
Classifier: Programming Language :: Python :: 3
License-File: LICENSE
Requires-Dist: Adafruit-Blinka
Requires-Dist: adafruit-circuitpython-busdevice
Requires-Dist: adafruit-circuitpython-register
Requires-Dist: toml
Provides-Extra: optional
